vibe_check_it/__init__.py
vibe_check_it/ai.py
vibe_check_it-0.1.3.dist-info/METADATA
vibe_check_it-0.1.3.dist-info/WHEEL
vibe_check_it-0.1.3.dist-info/licenses/LICENSE
vibe_check_it-0.1.3.dist-info/RECORD
