Metadata-Version: 2.4
Name: vibe-check-it
Version: 0.1.3
Summary: Check if your vibe functions are correctly vibing
Author-email: Ivan Ivanov <timee98@outlook.com>
License-File: LICENSE
Requires-Python: >=3.10
Requires-Dist: openai>=1.99.6
Requires-Dist: pydantic>=2.11.7
